<?xml version="1.0" encoding="utf-8"?><ctatt><tmst>20140102 11:27:21</tmst><errCd>0</errCd><errNm /><eta><staId>40460</staId><stpId>30090</stpId><staNm>Merchandise Mart</staNm><stpDe>Service toward Kimball or Linden</stpDe><rn>406</rn><rt>Brn</rt><destSt>30249</destSt><destNm>Kimball</destNm><trDr>1</trDr><prdt>20140102 11:26:50</prdt><arrT>20140102 11:29:50</arrT><isApp>0</isApp><isSch>0</isSch><isDly>0</isDly><isFlt>0</isFlt><flags /><lat>41.88574</lat><lon>-87.62783</lon><heading>270</heading></eta><eta><staId>40460</staId><stpId>30091</stpId><staNm>Merchandise Mart</staNm><stpDe>Service toward Loop</stpDe><rn>407</rn><rt>Brn</rt><destSt>30249</destSt><destNm>Loop</destNm><trDr>5</trDr><prdt>20140102 11:26:56</prdt><arrT>20140102 11:33:56</arrT><isApp>0</isApp><isSch>0</isSch><isDly>0</isDly><isFlt>0</isFlt><flags /><lat>41.91033</lat><lon>-87.64669</lon><heading>92</heading></eta><eta><staId>40460</staId><stpId>30090</stpId><staNm>Merchandise Mart</staNm><stpDe>Service toward Kimball or Linden</stpDe><rn>413</rn><rt>Brn</rt><destSt>30249</destSt><destNm>Kimball</destNm><trDr>1</trDr><prdt>20140102 11:26:47</prdt><arrT>20140102 11:34:47</arrT><isApp>0</isApp><isSch>0</isSch><isDly>0</isDly><isFlt>0</isFlt><flags /><lat>41.87694</lat><lon>-87.62738</lon><heading>88</heading></eta><eta><staId>40460</staId><stpId>30091</stpId><staNm>Merchandise Mart</staNm><stpDe>Service toward Loop</stpDe><rn>408</rn><rt>Brn</rt><destSt>30249</destSt><destNm>Loop</destNm><trDr>5</trDr><prdt>20140102 11:26:57</prdt><arrT>20140102 11:37:57</arrT><isApp>0</isApp><isSch>0</isSch><isDly>0</isDly><isFlt>0</isFlt><flags /><lat>41.92678</lat><lon>-87.65291</lon><heading>178</heading></eta></ctatt>