[{"timestamp":"20140101 20:32","stop_id":"1802","stop_name":"Clark & Bryn Mawr","id":"1783","predicted":"20140101 20:33","scheduled":"A","delayed":"","route":"50","direction":"Southbound","feet_left_to_stop":"145","datetime":"2014-01-01T20:33:00+00:00"},{"timestamp":"20140101 20:32","stop_id":"8955","stop_name":"Damen & Montrose","id":"1900","predicted":"20140101 20:34","scheduled":"A","delayed":"","route":"50","direction":"Northbound","feet_left_to_stop":"2335","datetime":"2014-01-01T20:34:00+00:00"},{"timestamp":"20140101 20:32","stop_id":"4954","stop_name":"Damen & Eastwood (Brown Line)","id":"1900","predicted":"20140101 20:36","scheduled":"A","delayed":"","route":"50","direction":"Northbound","feet_left_to_stop":"4163","datetime":"2014-01-01T20:36:00+00:00"},{"timestamp":"20140101 20:32","stop_id":"8816","stop_name":"Damen & Argyle","id":"1783","predicted":"20140101 20:39","scheduled":"A","delayed":"","route":"50","direction":"Southbound","feet_left_to_stop":"6987","datetime":"2014-01-01T20:39:00+00:00"},{"timestamp":"20140101 20:32","stop_id":"8819","stop_name":"Damen & Eastwood (Brown Line)","id":"1783","predicted":"20140101 20:41","scheduled":"A","delayed":"","route":"50","direction":"Southbound","feet_left_to_stop":"9324","datetime":"2014-01-01T20:41:00+00:00"},{"timestamp":"20140101 20:32","stop_id":"8942","stop_name":"Damen & Belmont","id":"1869","predicted":"20140101 20:42","scheduled":"A","delayed":"","route":"50","direction":"Northbound","feet_left_to_stop":"9453","datetime":"2014-01-01T20:42:00+00:00"},{"timestamp":"20140101 20:32","stop_id":"8951","stop_name":"Damen & Irving Park/Lincoln","id":"1869","predicted":"20140101 20:47","scheduled":"A","delayed":"","route":"50","direction":"Northbound","feet_left_to_stop":"14996","datetime":"2014-01-01T20:47:00+00:00"},{"timestamp":"20140101 20:32","stop_id":"8955","stop_name":"Damen & Montrose","id":"1869","predicted":"20140101 20:50","scheduled":"A","delayed":"","route":"50","direction":"Northbound","feet_left_to_stop":"17446","datetime":"2014-01-01T20:50:00+00:00"},{"timestamp":"20140101 20:32","stop_id":"1802","stop_name":"Clark & Bryn Mawr","id":"1900","predicted":"20140101 20:50","scheduled":"A","delayed":"","route":"50","direction":"Southbound","feet_left_to_stop":"14874","datetime":"2014-01-01T20:50:00+00:00"},{"timestamp":"20140101 20:32","stop_id":"4954","stop_name":"Damen & Eastwood (Brown Line)","id":"1869","predicted":"20140101 20:52","scheduled":"A","delayed":"","route":"50","direction":"Northbound","feet_left_to_stop":"19274","datetime":"2014-01-01T20:52:00+00:00"},{"timestamp":"20140101 20:32","stop_id":"8816","stop_name":"Damen & Argyle","id":"1900","predicted":"20140101 20:56","scheduled":"A","delayed":"","route":"50","direction":"Southbound","feet_left_to_stop":"21716","datetime":"2014-01-01T20:56:00+00:00"},{"timestamp":"20140101 20:32","stop_id":"8819","stop_name":"Damen & Eastwood (Brown Line)","id":"1900","predicted":"20140101 20:58","scheduled":"A","delayed":"","route":"50","direction":"Southbound","feet_left_to_stop":"24053","datetime":"2014-01-01T20:58:00+00:00"},{"timestamp":"20140101 20:32","stop_id":"8942","stop_name":"Damen & Belmont","id":"1885","predicted":"20140101 20:59","scheduled":"A","delayed":"","route":"50","direction":"Northbound","feet_left_to_stop":"26539","datetime":"2014-01-01T20:59:00+00:00"}]