[{"timestamp":"20131231 13:14","stop_id":"8816","stop_name":"Damen & Argyle","id":"1269","predicted":"20131231 13:17","scheduled":"A","delayed":"","route":"50","direction":"Southbound","feet_left_to_stop":"2528","datetime":"2013-12-31T13:17:00+00:00"},{"timestamp":"20131231 13:14","stop_id":"8955","stop_name":"Damen & Montrose","id":"1417","predicted":"20131231 13:17","scheduled":"A","delayed":"","route":"50","direction":"Northbound","feet_left_to_stop":"1891","datetime":"2013-12-31T13:17:00+00:00"},{"timestamp":"20131231 13:14","stop_id":"4954","stop_name":"Damen & Eastwood (Brown Line)","id":"1417","predicted":"20131231 13:19","scheduled":"A","delayed":"","route":"50","direction":"Northbound","feet_left_to_stop":"3719","datetime":"2013-12-31T13:19:00+00:00"},{"timestamp":"20131231 13:14","stop_id":"1802","stop_name":"Clark & Bryn Mawr","id":"1795","predicted":"20131231 13:19","scheduled":"A","delayed":"","route":"50","direction":"Southbound","feet_left_to_stop":"891","datetime":"2013-12-31T13:19:00+00:00"},{"timestamp":"20131231 13:14","stop_id":"8819","stop_name":"Damen & Eastwood (Brown Line)","id":"1269","predicted":"20131231 13:20","scheduled":"A","delayed":"","route":"50","direction":"Southbound","feet_left_to_stop":"4865","datetime":"2013-12-31T13:20:00+00:00"},{"timestamp":"20131231 13:14","stop_id":"8942","stop_name":"Damen & Belmont","id":"1420","predicted":"20131231 13:21","scheduled":"A","delayed":"","route":"50","direction":"Northbound","feet_left_to_stop":"5389","datetime":"2013-12-31T13:21:00+00:00"},{"timestamp":"20131231 13:14","stop_id":"8951","stop_name":"Damen & Irving Park/Lincoln","id":"1420","predicted":"20131231 13:27","scheduled":"A","delayed":"","route":"50","direction":"Northbound","feet_left_to_stop":"10932","datetime":"2013-12-31T13:27:00+00:00"},{"timestamp":"20131231 13:14","stop_id":"8816","stop_name":"Damen & Argyle","id":"1795","predicted":"20131231 13:27","scheduled":"A","delayed":"","route":"50","direction":"Southbound","feet_left_to_stop":"7733","datetime":"2013-12-31T13:27:00+00:00"},{"timestamp":"20131231 13:14","stop_id":"1802","stop_name":"Clark & Bryn Mawr","id":"1417","predicted":"20131231 13:30","scheduled":"A","delayed":"","route":"50","direction":"Southbound","feet_left_to_stop":"14430","datetime":"2013-12-31T13:30:00+00:00"},{"timestamp":"20131231 13:14","stop_id":"8955","stop_name":"Damen & Montrose","id":"1420","predicted":"20131231 13:30","scheduled":"A","delayed":"","route":"50","direction":"Northbound","feet_left_to_stop":"13382","datetime":"2013-12-31T13:30:00+00:00"},{"timestamp":"20131231 13:14","stop_id":"8819","stop_name":"Damen & Eastwood (Brown Line)","id":"1795","predicted":"20131231 13:30","scheduled":"A","delayed":"","route":"50","direction":"Southbound","feet_left_to_stop":"10070","datetime":"2013-12-31T13:30:00+00:00"},{"timestamp":"20131231 13:14","stop_id":"4954","stop_name":"Damen & Eastwood (Brown Line)","id":"1420","predicted":"20131231 13:32","scheduled":"A","delayed":"","route":"50","direction":"Northbound","feet_left_to_stop":"15210","datetime":"2013-12-31T13:32:00+00:00"},{"timestamp":"20131231 13:13","stop_id":"8942","stop_name":"Damen & Belmont","id":"1303","predicted":"20131231 13:34","scheduled":"A","delayed":"","route":"50","direction":"Northbound","feet_left_to_stop":"15959","datetime":"2013-12-31T13:34:00+00:00"},{"timestamp":"20131231 13:14","stop_id":"8816","stop_name":"Damen & Argyle","id":"1417","predicted":"20131231 13:38","scheduled":"A","delayed":"","route":"50","direction":"Southbound","feet_left_to_stop":"21272","datetime":"2013-12-31T13:38:00+00:00"},{"timestamp":"20131231 13:13","stop_id":"8951","stop_name":"Damen & Irving Park/Lincoln","id":"1303","predicted":"20131231 13:41","scheduled":"A","delayed":"","route":"50","direction":"Northbound","feet_left_to_stop":"21502","datetime":"2013-12-31T13:41:00+00:00"},{"timestamp":"20131231 13:14","stop_id":"8819","stop_name":"Damen & Eastwood (Brown Line)","id":"1417","predicted":"20131231 13:41","scheduled":"A","delayed":"","route":"50","direction":"Southbound","feet_left_to_stop":"23609","datetime":"2013-12-31T13:41:00+00:00"},{"timestamp":"20131231 13:13","stop_id":"8955","stop_name":"Damen & Montrose","id":"1303","predicted":"20131231 13:43","scheduled":"A","delayed":"","route":"50","direction":"Northbound","feet_left_to_stop":"23952","datetime":"2013-12-31T13:43:00+00:00"}]