[{"timestamp":"20140106 11:57","stop_id":"4954","stop_name":"Damen & Eastwood (Brown Line)","id":"1417","predicted":"20140106 11:59","scheduled":"A","delayed":"","route":"50","direction":"Northbound","feet_left_to_stop":"1040","datetime":"2014-01-06T11:59:00+00:00"},{"timestamp":"20140106 11:57","stop_id":"8942","stop_name":"Damen & Belmont","id":"1405","predicted":"20140106 12:01","scheduled":"A","delayed":"","route":"50","direction":"Northbound","feet_left_to_stop":"2742","datetime":"2014-01-06T12:01:00+00:00"},{"timestamp":"20140106 11:57","stop_id":"8816","stop_name":"Damen & Argyle","id":"1873","predicted":"20140106 12:01","scheduled":"A","delayed":"","route":"50","direction":"Southbound","feet_left_to_stop":"3745","datetime":"2014-01-06T12:01:00+00:00"},{"timestamp":"20140106 11:57","stop_id":"8819","stop_name":"Damen & Eastwood (Brown Line)","id":"1873","predicted":"20140106 12:04","scheduled":"A","delayed":"","route":"50","direction":"Southbound","feet_left_to_stop":"6082","datetime":"2014-01-06T12:04:00+00:00"},{"timestamp":"20140106 11:57","stop_id":"8951","stop_name":"Damen & Irving Park/Lincoln","id":"1405","predicted":"20140106 12:07","scheduled":"A","delayed":"","route":"50","direction":"Northbound","feet_left_to_stop":"8285","datetime":"2014-01-06T12:07:00+00:00"},{"timestamp":"20140106 11:57","stop_id":"1802","stop_name":"Clark & Bryn Mawr","id":"1429","predicted":"20140106 12:09","scheduled":"A","delayed":"","route":"50","direction":"Southbound","feet_left_to_stop":"1216","datetime":"2014-01-06T12:09:00+00:00"},{"timestamp":"20140106 11:57","stop_id":"8955","stop_name":"Damen & Montrose","id":"1405","predicted":"20140106 12:10","scheduled":"A","delayed":"","route":"50","direction":"Northbound","feet_left_to_stop":"10735","datetime":"2014-01-06T12:10:00+00:00"},{"timestamp":"20140106 11:57","stop_id":"4954","stop_name":"Damen & Eastwood (Brown Line)","id":"1405","predicted":"20140106 12:12","scheduled":"A","delayed":"","route":"50","direction":"Northbound","feet_left_to_stop":"12563","datetime":"2014-01-06T12:12:00+00:00"},{"timestamp":"20140106 11:57","stop_id":"8816","stop_name":"Damen & Argyle","id":"1429","predicted":"20140106 12:16","scheduled":"A","delayed":"","route":"50","direction":"Southbound","feet_left_to_stop":"8058","datetime":"2014-01-06T12:16:00+00:00"},{"timestamp":"20140106 11:57","stop_id":"8819","stop_name":"Damen & Eastwood (Brown Line)","id":"1429","predicted":"20140106 12:19","scheduled":"A","delayed":"","route":"50","direction":"Southbound","feet_left_to_stop":"10395","datetime":"2014-01-06T12:19:00+00:00"},{"timestamp":"20140106 11:57","stop_id":"8942","stop_name":"Damen & Belmont","id":"1388","predicted":"20140106 12:22","scheduled":"A","delayed":"","route":"50","direction":"Northbound","feet_left_to_stop":"19976","datetime":"2014-01-06T12:22:00+00:00"},{"timestamp":"20140106 11:57","stop_id":"1802","stop_name":"Clark & Bryn Mawr","id":"1417","predicted":"20140106 12:25","scheduled":"A","delayed":"","route":"50","direction":"Southbound","feet_left_to_stop":"11751","datetime":"2014-01-06T12:25:00+00:00"}]