[{"stop_id":"30018","stop_name":"Service toward Kimball","id":"401","predicted":"20140102 12:26:50","scheduled":"0","delayed":"0","route":"Brn","direction":"1","approaching":"0","fault":"0","station_id":"40090","station_name":"Damen","destination_stpd_id":"30249","destination_name":"Kimball","datetime":"2014-01-02T12:26:50+00:00","timestamp":"20140102 12:25:34"},{"stop_id":"30019","stop_name":"Service toward Loop","id":"415","predicted":"20140102 12:29:19","scheduled":"0","delayed":"0","route":"Brn","direction":"5","approaching":"0","fault":"0","station_id":"40090","station_name":"Damen","destination_stpd_id":"30249","destination_name":"Loop","datetime":"2014-01-02T12:29:19+00:00","timestamp":"20140102 12:25:34"},{"stop_id":"30018","stop_name":"Service toward Kimball","id":"409","predicted":"20140102 12:32:07","scheduled":"0","delayed":"0","route":"Brn","direction":"1","approaching":"0","fault":"0","station_id":"40090","station_name":"Damen","destination_stpd_id":"30249","destination_name":"Kimball","datetime":"2014-01-02T12:32:07+00:00","timestamp":"20140102 12:25:34"},{"stop_id":"30019","stop_name":"Service toward Loop","id":"406","predicted":"20140102 12:37:20","scheduled":"1","delayed":"0","route":"Brn","direction":"5","approaching":"0","fault":"0","station_id":"40090","station_name":"Damen","destination_stpd_id":"0","destination_name":"Loop","datetime":"2014-01-02T12:37:20+00:00","timestamp":"20140102 12:25:34"},{"stop_id":"30018","stop_name":"Service toward Kimball","id":"416","predicted":"20140102 12:40:53","scheduled":"0","delayed":"0","route":"Brn","direction":"1","approaching":"0","fault":"0","station_id":"40090","station_name":"Damen","destination_stpd_id":"30249","destination_name":"Kimball","datetime":"2014-01-02T12:40:53+00:00","timestamp":"20140102 12:25:34"}]